spectral/__init__.py
spectral/layers1d.py
spectral/layers2d.py
spectral/pooling.py
spectral/util.py
spectralLayersPyTorch-0.989.dist-info/METADATA
spectralLayersPyTorch-0.989.dist-info/RECORD
spectralLayersPyTorch-0.989.dist-info/WHEEL
spectralLayersPyTorch-0.989.dist-info/top_level.txt
