Metadata-Version: 2.1
Name: spectralLayersPyTorch
Version: 0.989
Summary: PyTorch NN based trainable spectral linear layers
Home-page: UNKNOWN
Author: Angela Botros & Narayan Schuetz
Author-email: narayan.schuetz@artorg.unibe.ch
License: MIT
Platform: UNKNOWN
Requires-Dist: torch
Requires-Dist: numpy
